anhaltai_commons_pl_hyper/__init__.py
anhaltai_commons_pl_hyper/callbacks.py
anhaltai_commons_pl_hyper/config_validation.py
anhaltai_commons_pl_hyper/constants.py
anhaltai_commons_pl_hyper/data_module.py
anhaltai_commons_pl_hyper/trainer.py
anhaltai_commons_pl_hyper/training_module.py
anhaltai_commons_pl_hyper/utils.py
anhaltai_commons_pl_hyper/dataclasses/__init__.py
anhaltai_commons_pl_hyper/dataclasses/callback.py
anhaltai_commons_pl_hyper/dataclasses/config.py
anhaltai_commons_pl_hyper/wandb_utils/__init__.py
anhaltai_commons_pl_hyper/wandb_utils/sweep_agent.py
anhaltai_commons_pl_hyper/wandb_utils/sweep_server.py
anhaltai_commons_pl_hyper-2025.2.4.dist-info/LICENSE
anhaltai_commons_pl_hyper-2025.2.4.dist-info/METADATA
anhaltai_commons_pl_hyper-2025.2.4.dist-info/WHEEL
anhaltai_commons_pl_hyper-2025.2.4.dist-info/top_level.txt
anhaltai_commons_pl_hyper-2025.2.4.dist-info/RECORD
