Metadata-Version: 2.2
Name: anhaltai-commons-pl-hyper
Version: 2025.2.4
Summary: Commons PyTorch Lightning Trainer for Hyperparmater Optimization
Author-email: Christian Hänig <christian.haenig@hs-anhalt.de>, Christian Gurski <christian.gurski@hs-anhalt.de>, Fabian Hanitzsch <fabian.hanitzsch@hs-anhalt.de>
Project-URL: Gitlab, https://gitlab.hs-anhalt.de/ki/projekte/anhaltai-commons/commons-pl-hyper
Classifier: Programming Language :: Python :: 3
Classifier: License :: OSI Approved :: MIT License
Classifier: Operating System :: OS Independent
Requires-Python: >=3.10
License-File: LICENSE
Requires-Dist: torch==2.2.2
Requires-Dist: numpy<=1.26.4,>=1.26.0
Requires-Dist: lightning>=2.4.0
Requires-Dist: wandb>=0.16.6
Requires-Dist: pyyaml>=6.0.1
Requires-Dist: torchvision>=0.17.2
Requires-Dist: datasets>=2.19.0
Requires-Dist: transformers>=4.40.1
Requires-Dist: python-dotenv>=1.0.1
Requires-Dist: requests>=2.32.3
Requires-Dist: uvicorn>=0.30.5
Requires-Dist: fastapi>=0.112.0
Requires-Dist: huggingface-hub>=0.23.4
Requires-Dist: scikit-learn>=1.5.1
Requires-Dist: strenum>=0.4.15
